{
    "os": "Windows-10-10.0.22000-SP0",
    "python": "3.8.0",
    "heartbeatAt": "2022-09-20T19:25:48.055347",
    "startedAt": "2022-09-20T19:25:47.651040",
    "docker": null,
    "gpu": "NVIDIA GeForce GTX 1660 Ti",
    "gpu_count": 1,
    "cpu_count": 12,
    "cuda": null,
    "args": [],
    "state": "running",
    "program": "load-train-model.py",
    "codePath": "load-train-model.py",
    "host": "XANDER-LAPTOP",
    "username": "ary93",
    "executable": "C:\\Users\\ary93\\AppData\\Local\\Programs\\Python\\Python38\\python.exe"
}
